upstream_weight/__init__.py
upstream_weight/traffic_model.py
upstream_weight/traffic_tune.py
upstream_weight-0.0.1.dist-info/LICENSE
upstream_weight-0.0.1.dist-info/METADATA
upstream_weight-0.0.1.dist-info/WHEEL
upstream_weight-0.0.1.dist-info/top_level.txt
upstream_weight-0.0.1.dist-info/RECORD
