Metadata-Version: 2.1
Name: upstream-weight
Version: 0.0.1
Summary: nginx upstream server weight
Home-page: https://github.com/xunull/upstream_weight
Author: xunull
Author-email: xunull@163.com
License: UNKNOWN
Platform: UNKNOWN
Classifier: Programming Language :: Python :: 3
Classifier: License :: OSI Approved :: Apache Software License
Classifier: Operating System :: OS Independent
Requires-Python: >=3.6
License-File: LICENSE
Requires-Dist: pydantic
